collective.externaleditor-2.0.0-py3.10-nspkg.pth
collective/externaleditor/__init__.py
collective/externaleditor/configure.zcml
collective/externaleditor/interfaces.py
collective/externaleditor/testing.py
collective/externaleditor/upgrades.py
collective/externaleditor/Extensions/install.py
collective/externaleditor/browser/__init__.py
collective/externaleditor/browser/configure.zcml
collective/externaleditor/browser/controlpanel.py
collective/externaleditor/browser/externaleditor.png
collective/externaleditor/browser/views.py
collective/externaleditor/locales/collective.externaleditor.pot
collective/externaleditor/locales/fr/LC_MESSAGES/collective.externaleditor.po
collective/externaleditor/profiles/default/actionicons.xml
collective/externaleditor/profiles/default/browserlayer.xml
collective/externaleditor/profiles/default/controlpanel.xml
collective/externaleditor/profiles/default/metadata.xml
collective/externaleditor/profiles/default/registry.xml
collective/externaleditor/profiles/default/rolemap.xml
collective/externaleditor/profiles/default/skins.xml
collective/externaleditor/profiles/uninstall/rolemap.xml
collective/externaleditor/profiles/uninstall/skins.xml
collective/externaleditor/skins/externaleditor/externalEditorEnabled.py
collective/externaleditor/skins/externaleditor/external_edit.py
collective/externaleditor/tests/__init__.py
collective/externaleditor/tests/controlpanel.txt
collective/externaleditor/tests/test_doctests.py
collective.externaleditor-2.0.0.dist-info/METADATA
collective.externaleditor-2.0.0.dist-info/WHEEL
collective.externaleditor-2.0.0.dist-info/entry_points.txt
collective.externaleditor-2.0.0.dist-info/namespace_packages.txt
collective.externaleditor-2.0.0.dist-info/top_level.txt
collective.externaleditor-2.0.0.dist-info/RECORD
