Metadata-Version: 2.1
Name: collective.externaleditor
Version: 2.0.0
Summary: Specific Plone layer for Products.ExternalEditor
Home-page: https://github.com/collective/collective.externaleditor/
Author: atReal
Author-email: contact@atreal.net
License: GPL
Keywords: Plone
Classifier: Development Status :: 5 - Production/Stable
Classifier: Framework :: Plone :: 5.2
Classifier: Framework :: Plone :: 6.0
Classifier: Framework :: Plone :: Addon
Classifier: Framework :: Plone
Classifier: Framework :: Plone
Classifier: Framework :: Zope :: 4
Classifier: Framework :: Zope :: 5
Classifier: Framework :: Zope
Classifier: License :: OSI Approved :: GNU General Public License (GPL)
Classifier: Programming Language :: Python :: 3 :: Only
Classifier: Programming Language :: Python :: 3.7
Classifier: Programming Language :: Python :: 3.8
Classifier: Programming Language :: Python :: 3.9
Classifier: Programming Language :: Python :: 3.10
Classifier: Programming Language :: Python :: 3.11
Classifier: Programming Language :: Python
Requires-Python: >=3.7
Requires-Dist: Plone
Requires-Dist: Products.CMFCore
Requires-Dist: Products.CMFPlone
Requires-Dist: Products.ExternalEditor >=1.1.0dev
Requires-Dist: Products.GenericSetup
Requires-Dist: Products.statusmessages
Requires-Dist: setuptools
Provides-Extra: test
Requires-Dist: plone.app.testing ; extra == 'test'
Requires-Dist: plone.app.robotframework[debug] ; extra == 'test'
